{
  "version": "v5.1.1-alpha.1.d131.ge6367fd2a",
  "details": {
    "url": "https://api.github.com/repos/MaaAssistantArknights/MaaRelease/releases/144485495",
    "assets_url": "https://api.github.com/repos/MaaAssistantArknights/MaaRelease/releases/144485495/assets",
    "upload_url": "https://uploads.github.com/repos/MaaAssistantArknights/MaaRelease/releases/144485495/assets{?name,label}",
    "html_url": "https://github.com/MaaAssistantArknights/MaaRelease/releases/tag/v5.1.1-alpha.1.d131.ge6367fd2a",
    "id": 144485495,
    "node_id": "RE_kwDOIUyZWc4InKx3",
    "tag_name": "v5.1.1-alpha.1.d131.ge6367fd2a",
    "target_commitish": "main",
    "name": "",
    "draft": false,
    "prerelease": true,
    "created_at": "2024-03-02T06:06:02Z",
    "published_at": "2024-03-02T06:08:58Z",
    "assets": [
      {
        "name": "MAA-v5.1.1-alpha.1.d131.ge6367fd2a-win-x64.zip",
        "size": 143583017,
        "browser_download_url": "https://github.com/MaaAssistantArknights/MaaRelease/releases/download/v5.1.1-alpha.1.d131.ge6367fd2a/MAA-v5.1.1-alpha.1.d131.ge6367fd2a-win-x64.zip",
        "mirrors": [
          "https://agent.imgg.dev/MaaAssistantArknights/MaaRelease/releases/download/v5.1.1-alpha.1.d131.ge6367fd2a/MAA-v5.1.1-alpha.1.d131.ge6367fd2a-win-x64.zip",
          "https://maa.r2.imgg.dev/MaaAssistantArknights/MaaRelease/releases/download/v5.1.1-alpha.1.d131.ge6367fd2a/MAA-v5.1.1-alpha.1.d131.ge6367fd2a-win-x64.zip"
        ]
      },
      {
        "name": "MAAComponent-OTA-v4.24.0_v5.1.1-alpha.1.d131.ge6367fd2a-win-x64.zip",
        "size": 40940076,
        "browser_download_url": "https://github.com/MaaAssistantArknights/MaaRelease/releases/download/v5.1.1-alpha.1.d131.ge6367fd2a/MAAComponent-OTA-v4.24.0_v5.1.1-alpha.1.d131.ge6367fd2a-win-x64.zip",
        "mirrors": [
          "https://agent.imgg.dev/MaaAssistantArknights/MaaRelease/releases/download/v5.1.1-alpha.1.d131.ge6367fd2a/MAAComponent-OTA-v4.24.0_v5.1.1-alpha.1.d131.ge6367fd2a-win-x64.zip",
          "https://maa.r2.imgg.dev/MaaAssistantArknights/MaaRelease/releases/download/v5.1.1-alpha.1.d131.ge6367fd2a/MAAComponent-OTA-v4.24.0_v5.1.1-alpha.1.d131.ge6367fd2a-win-x64.zip"
        ]
      },
      {
        "name": "MAAComponent-OTA-v4.25.0-beta.1_v5.1.1-alpha.1.d131.ge6367fd2a-win-x64.zip",
        "size": 40824584,
        "browser_download_url": "https://github.com/MaaAssistantArknights/MaaRelease/releases/download/v5.1.1-alpha.1.d131.ge6367fd2a/MAAComponent-OTA-v4.25.0-beta.1_v5.1.1-alpha.1.d131.ge6367fd2a-win-x64.zip",
        "mirrors": [
          "https://agent.imgg.dev/MaaAssistantArknights/MaaRelease/releases/download/v5.1.1-alpha.1.d131.ge6367fd2a/MAAComponent-OTA-v4.25.0-beta.1_v5.1.1-alpha.1.d131.ge6367fd2a-win-x64.zip",
          "https://maa.r2.imgg.dev/MaaAssistantArknights/MaaRelease/releases/download/v5.1.1-alpha.1.d131.ge6367fd2a/MAAComponent-OTA-v4.25.0-beta.1_v5.1.1-alpha.1.d131.ge6367fd2a-win-x64.zip"
        ]
      },
      {
        "name": "MAAComponent-OTA-v4.25.0-beta.2_v5.1.1-alpha.1.d131.ge6367fd2a-win-x64.zip",
        "size": 40383112,
        "browser_download_url": "https://github.com/MaaAssistantArknights/MaaRelease/releases/download/v5.1.1-alpha.1.d131.ge6367fd2a/MAAComponent-OTA-v4.25.0-beta.2_v5.1.1-alpha.1.d131.ge6367fd2a-win-x64.zip",
        "mirrors": [
          "https://agent.imgg.dev/MaaAssistantArknights/MaaRelease/releases/download/v5.1.1-alpha.1.d131.ge6367fd2a/MAAComponent-OTA-v4.25.0-beta.2_v5.1.1-alpha.1.d131.ge6367fd2a-win-x64.zip",
          "https://maa.r2.imgg.dev/MaaAssistantArknights/MaaRelease/releases/download/v5.1.1-alpha.1.d131.ge6367fd2a/MAAComponent-OTA-v4.25.0-beta.2_v5.1.1-alpha.1.d131.ge6367fd2a-win-x64.zip"
        ]
      },
      {
        "name": "MAAComponent-OTA-v4.25.0-beta.3_v5.1.1-alpha.1.d131.ge6367fd2a-win-x64.zip",
        "size": 40383112,
        "browser_download_url": "https://github.com/MaaAssistantArknights/MaaRelease/releases/download/v5.1.1-alpha.1.d131.ge6367fd2a/MAAComponent-OTA-v4.25.0-beta.3_v5.1.1-alpha.1.d131.ge6367fd2a-win-x64.zip",
        "mirrors": [
          "https://agent.imgg.dev/MaaAssistantArknights/MaaRelease/releases/download/v5.1.1-alpha.1.d131.ge6367fd2a/MAAComponent-OTA-v4.25.0-beta.3_v5.1.1-alpha.1.d131.ge6367fd2a-win-x64.zip",
          "https://maa.r2.imgg.dev/MaaAssistantArknights/MaaRelease/releases/download/v5.1.1-alpha.1.d131.ge6367fd2a/MAAComponent-OTA-v4.25.0-beta.3_v5.1.1-alpha.1.d131.ge6367fd2a-win-x64.zip"
        ]
      },
      {
        "name": "MAAComponent-OTA-v4.25.0_v5.1.1-alpha.1.d131.ge6367fd2a-win-x64.zip",
        "size": 40383112,
        "browser_download_url": "https://github.com/MaaAssistantArknights/MaaRelease/releases/download/v5.1.1-alpha.1.d131.ge6367fd2a/MAAComponent-OTA-v4.25.0_v5.1.1-alpha.1.d131.ge6367fd2a-win-x64.zip",
        "mirrors": [
          "https://agent.imgg.dev/MaaAssistantArknights/MaaRelease/releases/download/v5.1.1-alpha.1.d131.ge6367fd2a/MAAComponent-OTA-v4.25.0_v5.1.1-alpha.1.d131.ge6367fd2a-win-x64.zip",
          "https://maa.r2.imgg.dev/MaaAssistantArknights/MaaRelease/releases/download/v5.1.1-alpha.1.d131.ge6367fd2a/MAAComponent-OTA-v4.25.0_v5.1.1-alpha.1.d131.ge6367fd2a-win-x64.zip"
        ]
      },
      {
        "name": "MAAComponent-OTA-v4.26.0-beta.1_v5.1.1-alpha.1.d131.ge6367fd2a-win-x64.zip",
        "size": 40381593,
        "browser_download_url": "https://github.com/MaaAssistantArknights/MaaRelease/releases/download/v5.1.1-alpha.1.d131.ge6367fd2a/MAAComponent-OTA-v4.26.0-beta.1_v5.1.1-alpha.1.d131.ge6367fd2a-win-x64.zip",
        "mirrors": [
          "https://agent.imgg.dev/MaaAssistantArknights/MaaRelease/releases/download/v5.1.1-alpha.1.d131.ge6367fd2a/MAAComponent-OTA-v4.26.0-beta.1_v5.1.1-alpha.1.d131.ge6367fd2a-win-x64.zip",
          "https://maa.r2.imgg.dev/MaaAssistantArknights/MaaRelease/releases/download/v5.1.1-alpha.1.d131.ge6367fd2a/MAAComponent-OTA-v4.26.0-beta.1_v5.1.1-alpha.1.d131.ge6367fd2a-win-x64.zip"
        ]
      },
      {
        "name": "MAAComponent-OTA-v4.26.0-beta.2_v5.1.1-alpha.1.d131.ge6367fd2a-win-x64.zip",
        "size": 40294288,
        "browser_download_url": "https://github.com/MaaAssistantArknights/MaaRelease/releases/download/v5.1.1-alpha.1.d131.ge6367fd2a/MAAComponent-OTA-v4.26.0-beta.2_v5.1.1-alpha.1.d131.ge6367fd2a-win-x64.zip",
        "mirrors": [
          "https://agent.imgg.dev/MaaAssistantArknights/MaaRelease/releases/download/v5.1.1-alpha.1.d131.ge6367fd2a/MAAComponent-OTA-v4.26.0-beta.2_v5.1.1-alpha.1.d131.ge6367fd2a-win-x64.zip",
          "https://maa.r2.imgg.dev/MaaAssistantArknights/MaaRelease/releases/download/v5.1.1-alpha.1.d131.ge6367fd2a/MAAComponent-OTA-v4.26.0-beta.2_v5.1.1-alpha.1.d131.ge6367fd2a-win-x64.zip"
        ]
      },
      {
        "name": "MAAComponent-OTA-v4.26.0-beta.3_v5.1.1-alpha.1.d131.ge6367fd2a-win-x64.zip",
        "size": 40288857,
        "browser_download_url": "https://github.com/MaaAssistantArknights/MaaRelease/releases/download/v5.1.1-alpha.1.d131.ge6367fd2a/MAAComponent-OTA-v4.26.0-beta.3_v5.1.1-alpha.1.d131.ge6367fd2a-win-x64.zip",
        "mirrors": [
          "https://agent.imgg.dev/MaaAssistantArknights/MaaRelease/releases/download/v5.1.1-alpha.1.d131.ge6367fd2a/MAAComponent-OTA-v4.26.0-beta.3_v5.1.1-alpha.1.d131.ge6367fd2a-win-x64.zip",
          "https://maa.r2.imgg.dev/MaaAssistantArknights/MaaRelease/releases/download/v5.1.1-alpha.1.d131.ge6367fd2a/MAAComponent-OTA-v4.26.0-beta.3_v5.1.1-alpha.1.d131.ge6367fd2a-win-x64.zip"
        ]
      },
      {
        "name": "MAAComponent-OTA-v4.26.0_v5.1.1-alpha.1.d131.ge6367fd2a-win-x64.zip",
        "size": 40288857,
        "browser_download_url": "https://github.com/MaaAssistantArknights/MaaRelease/releases/download/v5.1.1-alpha.1.d131.ge6367fd2a/MAAComponent-OTA-v4.26.0_v5.1.1-alpha.1.d131.ge6367fd2a-win-x64.zip",
        "mirrors": [
          "https://agent.imgg.dev/MaaAssistantArknights/MaaRelease/releases/download/v5.1.1-alpha.1.d131.ge6367fd2a/MAAComponent-OTA-v4.26.0_v5.1.1-alpha.1.d131.ge6367fd2a-win-x64.zip",
          "https://maa.r2.imgg.dev/MaaAssistantArknights/MaaRelease/releases/download/v5.1.1-alpha.1.d131.ge6367fd2a/MAAComponent-OTA-v4.26.0_v5.1.1-alpha.1.d131.ge6367fd2a-win-x64.zip"
        ]
      },
      {
        "name": "MAAComponent-OTA-v4.26.1_v5.1.1-alpha.1.d131.ge6367fd2a-win-x64.zip",
        "size": 40044953,
        "browser_download_url": "https://github.com/MaaAssistantArknights/MaaRelease/releases/download/v5.1.1-alpha.1.d131.ge6367fd2a/MAAComponent-OTA-v4.26.1_v5.1.1-alpha.1.d131.ge6367fd2a-win-x64.zip",
        "mirrors": [
          "https://agent.imgg.dev/MaaAssistantArknights/MaaRelease/releases/download/v5.1.1-alpha.1.d131.ge6367fd2a/MAAComponent-OTA-v4.26.1_v5.1.1-alpha.1.d131.ge6367fd2a-win-x64.zip",
          "https://maa.r2.imgg.dev/MaaAssistantArknights/MaaRelease/releases/download/v5.1.1-alpha.1.d131.ge6367fd2a/MAAComponent-OTA-v4.26.1_v5.1.1-alpha.1.d131.ge6367fd2a-win-x64.zip"
        ]
      },
      {
        "name": "MAAComponent-OTA-v4.27.0-beta.1_v5.1.1-alpha.1.d131.ge6367fd2a-win-x64.zip",
        "size": 40023390,
        "browser_download_url": "https://github.com/MaaAssistantArknights/MaaRelease/releases/download/v5.1.1-alpha.1.d131.ge6367fd2a/MAAComponent-OTA-v4.27.0-beta.1_v5.1.1-alpha.1.d131.ge6367fd2a-win-x64.zip",
        "mirrors": [
          "https://agent.imgg.dev/MaaAssistantArknights/MaaRelease/releases/download/v5.1.1-alpha.1.d131.ge6367fd2a/MAAComponent-OTA-v4.27.0-beta.1_v5.1.1-alpha.1.d131.ge6367fd2a-win-x64.zip",
          "https://maa.r2.imgg.dev/MaaAssistantArknights/MaaRelease/releases/download/v5.1.1-alpha.1.d131.ge6367fd2a/MAAComponent-OTA-v4.27.0-beta.1_v5.1.1-alpha.1.d131.ge6367fd2a-win-x64.zip"
        ]
      },
      {
        "name": "MAAComponent-OTA-v4.27.0_v5.1.1-alpha.1.d131.ge6367fd2a-win-x64.zip",
        "size": 39648140,
        "browser_download_url": "https://github.com/MaaAssistantArknights/MaaRelease/releases/download/v5.1.1-alpha.1.d131.ge6367fd2a/MAAComponent-OTA-v4.27.0_v5.1.1-alpha.1.d131.ge6367fd2a-win-x64.zip",
        "mirrors": [
          "https://agent.imgg.dev/MaaAssistantArknights/MaaRelease/releases/download/v5.1.1-alpha.1.d131.ge6367fd2a/MAAComponent-OTA-v4.27.0_v5.1.1-alpha.1.d131.ge6367fd2a-win-x64.zip",
          "https://maa.r2.imgg.dev/MaaAssistantArknights/MaaRelease/releases/download/v5.1.1-alpha.1.d131.ge6367fd2a/MAAComponent-OTA-v4.27.0_v5.1.1-alpha.1.d131.ge6367fd2a-win-x64.zip"
        ]
      },
      {
        "name": "MAAComponent-OTA-v4.27.1_v5.1.1-alpha.1.d131.ge6367fd2a-win-x64.zip",
        "size": 39648140,
        "browser_download_url": "https://github.com/MaaAssistantArknights/MaaRelease/releases/download/v5.1.1-alpha.1.d131.ge6367fd2a/MAAComponent-OTA-v4.27.1_v5.1.1-alpha.1.d131.ge6367fd2a-win-x64.zip",
        "mirrors": [
          "https://agent.imgg.dev/MaaAssistantArknights/MaaRelease/releases/download/v5.1.1-alpha.1.d131.ge6367fd2a/MAAComponent-OTA-v4.27.1_v5.1.1-alpha.1.d131.ge6367fd2a-win-x64.zip",
          "https://maa.r2.imgg.dev/MaaAssistantArknights/MaaRelease/releases/download/v5.1.1-alpha.1.d131.ge6367fd2a/MAAComponent-OTA-v4.27.1_v5.1.1-alpha.1.d131.ge6367fd2a-win-x64.zip"
        ]
      },
      {
        "name": "MAAComponent-OTA-v4.28.0-beta.1_v5.1.1-alpha.1.d131.ge6367fd2a-win-x64.zip",
        "size": 39642947,
        "browser_download_url": "https://github.com/MaaAssistantArknights/MaaRelease/releases/download/v5.1.1-alpha.1.d131.ge6367fd2a/MAAComponent-OTA-v4.28.0-beta.1_v5.1.1-alpha.1.d131.ge6367fd2a-win-x64.zip",
        "mirrors": [
          "https://agent.imgg.dev/MaaAssistantArknights/MaaRelease/releases/download/v5.1.1-alpha.1.d131.ge6367fd2a/MAAComponent-OTA-v4.28.0-beta.1_v5.1.1-alpha.1.d131.ge6367fd2a-win-x64.zip",
          "https://maa.r2.imgg.dev/MaaAssistantArknights/MaaRelease/releases/download/v5.1.1-alpha.1.d131.ge6367fd2a/MAAComponent-OTA-v4.28.0-beta.1_v5.1.1-alpha.1.d131.ge6367fd2a-win-x64.zip"
        ]
      },
      {
        "name": "MAAComponent-OTA-v4.28.0-beta.2_v5.1.1-alpha.1.d131.ge6367fd2a-win-x64.zip",
        "size": 39583517,
        "browser_download_url": "https://github.com/MaaAssistantArknights/MaaRelease/releases/download/v5.1.1-alpha.1.d131.ge6367fd2a/MAAComponent-OTA-v4.28.0-beta.2_v5.1.1-alpha.1.d131.ge6367fd2a-win-x64.zip",
        "mirrors": [
          "https://agent.imgg.dev/MaaAssistantArknights/MaaRelease/releases/download/v5.1.1-alpha.1.d131.ge6367fd2a/MAAComponent-OTA-v4.28.0-beta.2_v5.1.1-alpha.1.d131.ge6367fd2a-win-x64.zip",
          "https://maa.r2.imgg.dev/MaaAssistantArknights/MaaRelease/releases/download/v5.1.1-alpha.1.d131.ge6367fd2a/MAAComponent-OTA-v4.28.0-beta.2_v5.1.1-alpha.1.d131.ge6367fd2a-win-x64.zip"
        ]
      },
      {
        "name": "MAAComponent-OTA-v4.28.0_v5.1.1-alpha.1.d131.ge6367fd2a-win-x64.zip",
        "size": 39583490,
        "browser_download_url": "https://github.com/MaaAssistantArknights/MaaRelease/releases/download/v5.1.1-alpha.1.d131.ge6367fd2a/MAAComponent-OTA-v4.28.0_v5.1.1-alpha.1.d131.ge6367fd2a-win-x64.zip",
        "mirrors": [
          "https://agent.imgg.dev/MaaAssistantArknights/MaaRelease/releases/download/v5.1.1-alpha.1.d131.ge6367fd2a/MAAComponent-OTA-v4.28.0_v5.1.1-alpha.1.d131.ge6367fd2a-win-x64.zip",
          "https://maa.r2.imgg.dev/MaaAssistantArknights/MaaRelease/releases/download/v5.1.1-alpha.1.d131.ge6367fd2a/MAAComponent-OTA-v4.28.0_v5.1.1-alpha.1.d131.ge6367fd2a-win-x64.zip"
        ]
      },
      {
        "name": "MAAComponent-OTA-v4.28.1_v5.1.1-alpha.1.d131.ge6367fd2a-win-x64.zip",
        "size": 39545834,
        "browser_download_url": "https://github.com/MaaAssistantArknights/MaaRelease/releases/download/v5.1.1-alpha.1.d131.ge6367fd2a/MAAComponent-OTA-v4.28.1_v5.1.1-alpha.1.d131.ge6367fd2a-win-x64.zip",
        "mirrors": [
          "https://agent.imgg.dev/MaaAssistantArknights/MaaRelease/releases/download/v5.1.1-alpha.1.d131.ge6367fd2a/MAAComponent-OTA-v4.28.1_v5.1.1-alpha.1.d131.ge6367fd2a-win-x64.zip",
          "https://maa.r2.imgg.dev/MaaAssistantArknights/MaaRelease/releases/download/v5.1.1-alpha.1.d131.ge6367fd2a/MAAComponent-OTA-v4.28.1_v5.1.1-alpha.1.d131.ge6367fd2a-win-x64.zip"
        ]
      },
      {
        "name": "MAAComponent-OTA-v4.28.2_v5.1.1-alpha.1.d131.ge6367fd2a-win-x64.zip",
        "size": 39545834,
        "browser_download_url": "https://github.com/MaaAssistantArknights/MaaRelease/releases/download/v5.1.1-alpha.1.d131.ge6367fd2a/MAAComponent-OTA-v4.28.2_v5.1.1-alpha.1.d131.ge6367fd2a-win-x64.zip",
        "mirrors": [
          "https://agent.imgg.dev/MaaAssistantArknights/MaaRelease/releases/download/v5.1.1-alpha.1.d131.ge6367fd2a/MAAComponent-OTA-v4.28.2_v5.1.1-alpha.1.d131.ge6367fd2a-win-x64.zip",
          "https://maa.r2.imgg.dev/MaaAssistantArknights/MaaRelease/releases/download/v5.1.1-alpha.1.d131.ge6367fd2a/MAAComponent-OTA-v4.28.2_v5.1.1-alpha.1.d131.ge6367fd2a-win-x64.zip"
        ]
      },
      {
        "name": "MAAComponent-OTA-v4.28.3_v5.1.1-alpha.1.d131.ge6367fd2a-win-x64.zip",
        "size": 39565190,
        "browser_download_url": "https://github.com/MaaAssistantArknights/MaaRelease/releases/download/v5.1.1-alpha.1.d131.ge6367fd2a/MAAComponent-OTA-v4.28.3_v5.1.1-alpha.1.d131.ge6367fd2a-win-x64.zip",
        "mirrors": [
          "https://agent.imgg.dev/MaaAssistantArknights/MaaRelease/releases/download/v5.1.1-alpha.1.d131.ge6367fd2a/MAAComponent-OTA-v4.28.3_v5.1.1-alpha.1.d131.ge6367fd2a-win-x64.zip",
          "https://maa.r2.imgg.dev/MaaAssistantArknights/MaaRelease/releases/download/v5.1.1-alpha.1.d131.ge6367fd2a/MAAComponent-OTA-v4.28.3_v5.1.1-alpha.1.d131.ge6367fd2a-win-x64.zip"
        ]
      },
      {
        "name": "MAAComponent-OTA-v4.28.4_v5.1.1-alpha.1.d131.ge6367fd2a-win-x64.zip",
        "size": 39562089,
        "browser_download_url": "https://github.com/MaaAssistantArknights/MaaRelease/releases/download/v5.1.1-alpha.1.d131.ge6367fd2a/MAAComponent-OTA-v4.28.4_v5.1.1-alpha.1.d131.ge6367fd2a-win-x64.zip",
        "mirrors": [
          "https://agent.imgg.dev/MaaAssistantArknights/MaaRelease/releases/download/v5.1.1-alpha.1.d131.ge6367fd2a/MAAComponent-OTA-v4.28.4_v5.1.1-alpha.1.d131.ge6367fd2a-win-x64.zip",
          "https://maa.r2.imgg.dev/MaaAssistantArknights/MaaRelease/releases/download/v5.1.1-alpha.1.d131.ge6367fd2a/MAAComponent-OTA-v4.28.4_v5.1.1-alpha.1.d131.ge6367fd2a-win-x64.zip"
        ]
      },
      {
        "name": "MAAComponent-OTA-v4.28.5_v5.1.1-alpha.1.d131.ge6367fd2a-win-x64.zip",
        "size": 39540606,
        "browser_download_url": "https://github.com/MaaAssistantArknights/MaaRelease/releases/download/v5.1.1-alpha.1.d131.ge6367fd2a/MAAComponent-OTA-v4.28.5_v5.1.1-alpha.1.d131.ge6367fd2a-win-x64.zip",
        "mirrors": [
          "https://agent.imgg.dev/MaaAssistantArknights/MaaRelease/releases/download/v5.1.1-alpha.1.d131.ge6367fd2a/MAAComponent-OTA-v4.28.5_v5.1.1-alpha.1.d131.ge6367fd2a-win-x64.zip",
          "https://maa.r2.imgg.dev/MaaAssistantArknights/MaaRelease/releases/download/v5.1.1-alpha.1.d131.ge6367fd2a/MAAComponent-OTA-v4.28.5_v5.1.1-alpha.1.d131.ge6367fd2a-win-x64.zip"
        ]
      },
      {
        "name": "MAAComponent-OTA-v4.28.6_v5.1.1-alpha.1.d131.ge6367fd2a-win-x64.zip",
        "size": 39540606,
        "browser_download_url": "https://github.com/MaaAssistantArknights/MaaRelease/releases/download/v5.1.1-alpha.1.d131.ge6367fd2a/MAAComponent-OTA-v4.28.6_v5.1.1-alpha.1.d131.ge6367fd2a-win-x64.zip",
        "mirrors": [
          "https://agent.imgg.dev/MaaAssistantArknights/MaaRelease/releases/download/v5.1.1-alpha.1.d131.ge6367fd2a/MAAComponent-OTA-v4.28.6_v5.1.1-alpha.1.d131.ge6367fd2a-win-x64.zip",
          "https://maa.r2.imgg.dev/MaaAssistantArknights/MaaRelease/releases/download/v5.1.1-alpha.1.d131.ge6367fd2a/MAAComponent-OTA-v4.28.6_v5.1.1-alpha.1.d131.ge6367fd2a-win-x64.zip"
        ]
      },
      {
        "name": "MAAComponent-OTA-v4.28.7_v5.1.1-alpha.1.d131.ge6367fd2a-win-x64.zip",
        "size": 39527952,
        "browser_download_url": "https://github.com/MaaAssistantArknights/MaaRelease/releases/download/v5.1.1-alpha.1.d131.ge6367fd2a/MAAComponent-OTA-v4.28.7_v5.1.1-alpha.1.d131.ge6367fd2a-win-x64.zip",
        "mirrors": [
          "https://agent.imgg.dev/MaaAssistantArknights/MaaRelease/releases/download/v5.1.1-alpha.1.d131.ge6367fd2a/MAAComponent-OTA-v4.28.7_v5.1.1-alpha.1.d131.ge6367fd2a-win-x64.zip",
          "https://maa.r2.imgg.dev/MaaAssistantArknights/MaaRelease/releases/download/v5.1.1-alpha.1.d131.ge6367fd2a/MAAComponent-OTA-v4.28.7_v5.1.1-alpha.1.d131.ge6367fd2a-win-x64.zip"
        ]
      },
      {
        "name": "MAAComponent-OTA-v4.28.8_v5.1.1-alpha.1.d131.ge6367fd2a-win-x64.zip",
        "size": 39509840,
        "browser_download_url": "https://github.com/MaaAssistantArknights/MaaRelease/releases/download/v5.1.1-alpha.1.d131.ge6367fd2a/MAAComponent-OTA-v4.28.8_v5.1.1-alpha.1.d131.ge6367fd2a-win-x64.zip",
        "mirrors": [
          "https://agent.imgg.dev/MaaAssistantArknights/MaaRelease/releases/download/v5.1.1-alpha.1.d131.ge6367fd2a/MAAComponent-OTA-v4.28.8_v5.1.1-alpha.1.d131.ge6367fd2a-win-x64.zip",
          "https://maa.r2.imgg.dev/MaaAssistantArknights/MaaRelease/releases/download/v5.1.1-alpha.1.d131.ge6367fd2a/MAAComponent-OTA-v4.28.8_v5.1.1-alpha.1.d131.ge6367fd2a-win-x64.zip"
        ]
      },
      {
        "name": "MAAComponent-OTA-v5.0.0-beta.1_v5.1.1-alpha.1.d131.ge6367fd2a-win-x64.zip",
        "size": 9396897,
        "browser_download_url": "https://github.com/MaaAssistantArknights/MaaRelease/releases/download/v5.1.1-alpha.1.d131.ge6367fd2a/MAAComponent-OTA-v5.0.0-beta.1_v5.1.1-alpha.1.d131.ge6367fd2a-win-x64.zip",
        "mirrors": [
          "https://agent.imgg.dev/MaaAssistantArknights/MaaRelease/releases/download/v5.1.1-alpha.1.d131.ge6367fd2a/MAAComponent-OTA-v5.0.0-beta.1_v5.1.1-alpha.1.d131.ge6367fd2a-win-x64.zip",
          "https://maa.r2.imgg.dev/MaaAssistantArknights/MaaRelease/releases/download/v5.1.1-alpha.1.d131.ge6367fd2a/MAAComponent-OTA-v5.0.0-beta.1_v5.1.1-alpha.1.d131.ge6367fd2a-win-x64.zip"
        ]
      },
      {
        "name": "MAAComponent-OTA-v5.0.0-beta.2_v5.1.1-alpha.1.d131.ge6367fd2a-win-x64.zip",
        "size": 9334121,
        "browser_download_url": "https://github.com/MaaAssistantArknights/MaaRelease/releases/download/v5.1.1-alpha.1.d131.ge6367fd2a/MAAComponent-OTA-v5.0.0-beta.2_v5.1.1-alpha.1.d131.ge6367fd2a-win-x64.zip",
        "mirrors": [
          "https://agent.imgg.dev/MaaAssistantArknights/MaaRelease/releases/download/v5.1.1-alpha.1.d131.ge6367fd2a/MAAComponent-OTA-v5.0.0-beta.2_v5.1.1-alpha.1.d131.ge6367fd2a-win-x64.zip",
          "https://maa.r2.imgg.dev/MaaAssistantArknights/MaaRelease/releases/download/v5.1.1-alpha.1.d131.ge6367fd2a/MAAComponent-OTA-v5.0.0-beta.2_v5.1.1-alpha.1.d131.ge6367fd2a-win-x64.zip"
        ]
      },
      {
        "name": "MAAComponent-OTA-v5.0.0_v5.1.1-alpha.1.d131.ge6367fd2a-win-x64.zip",
        "size": 8945533,
        "browser_download_url": "https://github.com/MaaAssistantArknights/MaaRelease/releases/download/v5.1.1-alpha.1.d131.ge6367fd2a/MAAComponent-OTA-v5.0.0_v5.1.1-alpha.1.d131.ge6367fd2a-win-x64.zip",
        "mirrors": [
          "https://agent.imgg.dev/MaaAssistantArknights/MaaRelease/releases/download/v5.1.1-alpha.1.d131.ge6367fd2a/MAAComponent-OTA-v5.0.0_v5.1.1-alpha.1.d131.ge6367fd2a-win-x64.zip",
          "https://maa.r2.imgg.dev/MaaAssistantArknights/MaaRelease/releases/download/v5.1.1-alpha.1.d131.ge6367fd2a/MAAComponent-OTA-v5.0.0_v5.1.1-alpha.1.d131.ge6367fd2a-win-x64.zip"
        ]
      },
      {
        "name": "MAAComponent-OTA-v5.1.0-beta.1.d041.g504067d9c_v5.1.1-alpha.1.d131.ge6367fd2a-win-x64.zip",
        "size": 8405383,
        "browser_download_url": "https://github.com/MaaAssistantArknights/MaaRelease/releases/download/v5.1.1-alpha.1.d131.ge6367fd2a/MAAComponent-OTA-v5.1.0-beta.1.d041.g504067d9c_v5.1.1-alpha.1.d131.ge6367fd2a-win-x64.zip",
        "mirrors": [
          "https://agent.imgg.dev/MaaAssistantArknights/MaaRelease/releases/download/v5.1.1-alpha.1.d131.ge6367fd2a/MAAComponent-OTA-v5.1.0-beta.1.d041.g504067d9c_v5.1.1-alpha.1.d131.ge6367fd2a-win-x64.zip",
          "https://maa.r2.imgg.dev/MaaAssistantArknights/MaaRelease/releases/download/v5.1.1-alpha.1.d131.ge6367fd2a/MAAComponent-OTA-v5.1.0-beta.1.d041.g504067d9c_v5.1.1-alpha.1.d131.ge6367fd2a-win-x64.zip"
        ]
      },
      {
        "name": "MAAComponent-OTA-v5.1.0-beta.1.d043.g7e3782433_v5.1.1-alpha.1.d131.ge6367fd2a-win-x64.zip",
        "size": 8405383,
        "browser_download_url": "https://github.com/MaaAssistantArknights/MaaRelease/releases/download/v5.1.1-alpha.1.d131.ge6367fd2a/MAAComponent-OTA-v5.1.0-beta.1.d043.g7e3782433_v5.1.1-alpha.1.d131.ge6367fd2a-win-x64.zip",
        "mirrors": [
          "https://agent.imgg.dev/MaaAssistantArknights/MaaRelease/releases/download/v5.1.1-alpha.1.d131.ge6367fd2a/MAAComponent-OTA-v5.1.0-beta.1.d043.g7e3782433_v5.1.1-alpha.1.d131.ge6367fd2a-win-x64.zip",
          "https://maa.r2.imgg.dev/MaaAssistantArknights/MaaRelease/releases/download/v5.1.1-alpha.1.d131.ge6367fd2a/MAAComponent-OTA-v5.1.0-beta.1.d043.g7e3782433_v5.1.1-alpha.1.d131.ge6367fd2a-win-x64.zip"
        ]
      },
      {
        "name": "MAAComponent-OTA-v5.1.0-beta.1.d059.gc790e5cfc_v5.1.1-alpha.1.d131.ge6367fd2a-win-x64.zip",
        "size": 8384061,
        "browser_download_url": "https://github.com/MaaAssistantArknights/MaaRelease/releases/download/v5.1.1-alpha.1.d131.ge6367fd2a/MAAComponent-OTA-v5.1.0-beta.1.d059.gc790e5cfc_v5.1.1-alpha.1.d131.ge6367fd2a-win-x64.zip",
        "mirrors": [
          "https://agent.imgg.dev/MaaAssistantArknights/MaaRelease/releases/download/v5.1.1-alpha.1.d131.ge6367fd2a/MAAComponent-OTA-v5.1.0-beta.1.d059.gc790e5cfc_v5.1.1-alpha.1.d131.ge6367fd2a-win-x64.zip",
          "https://maa.r2.imgg.dev/MaaAssistantArknights/MaaRelease/releases/download/v5.1.1-alpha.1.d131.ge6367fd2a/MAAComponent-OTA-v5.1.0-beta.1.d059.gc790e5cfc_v5.1.1-alpha.1.d131.ge6367fd2a-win-x64.zip"
        ]
      },
      {
        "name": "MAAComponent-OTA-v5.1.0-beta.1.d073.gd3e3ecd42_v5.1.1-alpha.1.d131.ge6367fd2a-win-x64.zip",
        "size": 8354065,
        "browser_download_url": "https://github.com/MaaAssistantArknights/MaaRelease/releases/download/v5.1.1-alpha.1.d131.ge6367fd2a/MAAComponent-OTA-v5.1.0-beta.1.d073.gd3e3ecd42_v5.1.1-alpha.1.d131.ge6367fd2a-win-x64.zip",
        "mirrors": [
          "https://agent.imgg.dev/MaaAssistantArknights/MaaRelease/releases/download/v5.1.1-alpha.1.d131.ge6367fd2a/MAAComponent-OTA-v5.1.0-beta.1.d073.gd3e3ecd42_v5.1.1-alpha.1.d131.ge6367fd2a-win-x64.zip",
          "https://maa.r2.imgg.dev/MaaAssistantArknights/MaaRelease/releases/download/v5.1.1-alpha.1.d131.ge6367fd2a/MAAComponent-OTA-v5.1.0-beta.1.d073.gd3e3ecd42_v5.1.1-alpha.1.d131.ge6367fd2a-win-x64.zip"
        ]
      },
      {
        "name": "MAAComponent-OTA-v5.1.0-beta.1.d086.g1d39b0fbd_v5.1.1-alpha.1.d131.ge6367fd2a-win-x64.zip",
        "size": 8331863,
        "browser_download_url": "https://github.com/MaaAssistantArknights/MaaRelease/releases/download/v5.1.1-alpha.1.d131.ge6367fd2a/MAAComponent-OTA-v5.1.0-beta.1.d086.g1d39b0fbd_v5.1.1-alpha.1.d131.ge6367fd2a-win-x64.zip",
        "mirrors": [
          "https://agent.imgg.dev/MaaAssistantArknights/MaaRelease/releases/download/v5.1.1-alpha.1.d131.ge6367fd2a/MAAComponent-OTA-v5.1.0-beta.1.d086.g1d39b0fbd_v5.1.1-alpha.1.d131.ge6367fd2a-win-x64.zip",
          "https://maa.r2.imgg.dev/MaaAssistantArknights/MaaRelease/releases/download/v5.1.1-alpha.1.d131.ge6367fd2a/MAAComponent-OTA-v5.1.0-beta.1.d086.g1d39b0fbd_v5.1.1-alpha.1.d131.ge6367fd2a-win-x64.zip"
        ]
      },
      {
        "name": "MAAComponent-OTA-v5.1.0-beta.1.d089.g369b57ec3_v5.1.1-alpha.1.d131.ge6367fd2a-win-x64.zip",
        "size": 8329181,
        "browser_download_url": "https://github.com/MaaAssistantArknights/MaaRelease/releases/download/v5.1.1-alpha.1.d131.ge6367fd2a/MAAComponent-OTA-v5.1.0-beta.1.d089.g369b57ec3_v5.1.1-alpha.1.d131.ge6367fd2a-win-x64.zip",
        "mirrors": [
          "https://agent.imgg.dev/MaaAssistantArknights/MaaRelease/releases/download/v5.1.1-alpha.1.d131.ge6367fd2a/MAAComponent-OTA-v5.1.0-beta.1.d089.g369b57ec3_v5.1.1-alpha.1.d131.ge6367fd2a-win-x64.zip",
          "https://maa.r2.imgg.dev/MaaAssistantArknights/MaaRelease/releases/download/v5.1.1-alpha.1.d131.ge6367fd2a/MAAComponent-OTA-v5.1.0-beta.1.d089.g369b57ec3_v5.1.1-alpha.1.d131.ge6367fd2a-win-x64.zip"
        ]
      },
      {
        "name": "MAAComponent-OTA-v5.1.0-beta.1_v5.1.1-alpha.1.d131.ge6367fd2a-win-x64.zip",
        "size": 8443416,
        "browser_download_url": "https://github.com/MaaAssistantArknights/MaaRelease/releases/download/v5.1.1-alpha.1.d131.ge6367fd2a/MAAComponent-OTA-v5.1.0-beta.1_v5.1.1-alpha.1.d131.ge6367fd2a-win-x64.zip",
        "mirrors": [
          "https://agent.imgg.dev/MaaAssistantArknights/MaaRelease/releases/download/v5.1.1-alpha.1.d131.ge6367fd2a/MAAComponent-OTA-v5.1.0-beta.1_v5.1.1-alpha.1.d131.ge6367fd2a-win-x64.zip",
          "https://maa.r2.imgg.dev/MaaAssistantArknights/MaaRelease/releases/download/v5.1.1-alpha.1.d131.ge6367fd2a/MAAComponent-OTA-v5.1.0-beta.1_v5.1.1-alpha.1.d131.ge6367fd2a-win-x64.zip"
        ]
      },
      {
        "name": "MAAComponent-OTA-v5.1.0-beta.2.d004.g4fcfa56b1_v5.1.1-alpha.1.d131.ge6367fd2a-win-x64.zip",
        "size": 8329181,
        "browser_download_url": "https://github.com/MaaAssistantArknights/MaaRelease/releases/download/v5.1.1-alpha.1.d131.ge6367fd2a/MAAComponent-OTA-v5.1.0-beta.2.d004.g4fcfa56b1_v5.1.1-alpha.1.d131.ge6367fd2a-win-x64.zip",
        "mirrors": [
          "https://agent.imgg.dev/MaaAssistantArknights/MaaRelease/releases/download/v5.1.1-alpha.1.d131.ge6367fd2a/MAAComponent-OTA-v5.1.0-beta.2.d004.g4fcfa56b1_v5.1.1-alpha.1.d131.ge6367fd2a-win-x64.zip",
          "https://maa.r2.imgg.dev/MaaAssistantArknights/MaaRelease/releases/download/v5.1.1-alpha.1.d131.ge6367fd2a/MAAComponent-OTA-v5.1.0-beta.2.d004.g4fcfa56b1_v5.1.1-alpha.1.d131.ge6367fd2a-win-x64.zip"
        ]
      },
      {
        "name": "MAAComponent-OTA-v5.1.0-beta.2.d009.g8dca4d31d_v5.1.1-alpha.1.d131.ge6367fd2a-win-x64.zip",
        "size": 8298558,
        "browser_download_url": "https://github.com/MaaAssistantArknights/MaaRelease/releases/download/v5.1.1-alpha.1.d131.ge6367fd2a/MAAComponent-OTA-v5.1.0-beta.2.d009.g8dca4d31d_v5.1.1-alpha.1.d131.ge6367fd2a-win-x64.zip",
        "mirrors": [
          "https://agent.imgg.dev/MaaAssistantArknights/MaaRelease/releases/download/v5.1.1-alpha.1.d131.ge6367fd2a/MAAComponent-OTA-v5.1.0-beta.2.d009.g8dca4d31d_v5.1.1-alpha.1.d131.ge6367fd2a-win-x64.zip",
          "https://maa.r2.imgg.dev/MaaAssistantArknights/MaaRelease/releases/download/v5.1.1-alpha.1.d131.ge6367fd2a/MAAComponent-OTA-v5.1.0-beta.2.d009.g8dca4d31d_v5.1.1-alpha.1.d131.ge6367fd2a-win-x64.zip"
        ]
      },
      {
        "name": "MAAComponent-OTA-v5.1.0-beta.2_v5.1.1-alpha.1.d131.ge6367fd2a-win-x64.zip",
        "size": 8329181,
        "browser_download_url": "https://github.com/MaaAssistantArknights/MaaRelease/releases/download/v5.1.1-alpha.1.d131.ge6367fd2a/MAAComponent-OTA-v5.1.0-beta.2_v5.1.1-alpha.1.d131.ge6367fd2a-win-x64.zip",
        "mirrors": [
          "https://agent.imgg.dev/MaaAssistantArknights/MaaRelease/releases/download/v5.1.1-alpha.1.d131.ge6367fd2a/MAAComponent-OTA-v5.1.0-beta.2_v5.1.1-alpha.1.d131.ge6367fd2a-win-x64.zip",
          "https://maa.r2.imgg.dev/MaaAssistantArknights/MaaRelease/releases/download/v5.1.1-alpha.1.d131.ge6367fd2a/MAAComponent-OTA-v5.1.0-beta.2_v5.1.1-alpha.1.d131.ge6367fd2a-win-x64.zip"
        ]
      },
      {
        "name": "MAAComponent-OTA-v5.1.0_v5.1.1-alpha.1.d131.ge6367fd2a-win-x64.zip",
        "size": 8298558,
        "browser_download_url": "https://github.com/MaaAssistantArknights/MaaRelease/releases/download/v5.1.1-alpha.1.d131.ge6367fd2a/MAAComponent-OTA-v5.1.0_v5.1.1-alpha.1.d131.ge6367fd2a-win-x64.zip",
        "mirrors": [
          "https://agent.imgg.dev/MaaAssistantArknights/MaaRelease/releases/download/v5.1.1-alpha.1.d131.ge6367fd2a/MAAComponent-OTA-v5.1.0_v5.1.1-alpha.1.d131.ge6367fd2a-win-x64.zip",
          "https://maa.r2.imgg.dev/MaaAssistantArknights/MaaRelease/releases/download/v5.1.1-alpha.1.d131.ge6367fd2a/MAAComponent-OTA-v5.1.0_v5.1.1-alpha.1.d131.ge6367fd2a-win-x64.zip"
        ]
      },
      {
        "name": "MAAComponent-OTA-v5.1.1-alpha.1.d006.g91b0b8e4f_v5.1.1-alpha.1.d131.ge6367fd2a-win-x64.zip",
        "size": 8298558,
        "browser_download_url": "https://github.com/MaaAssistantArknights/MaaRelease/releases/download/v5.1.1-alpha.1.d131.ge6367fd2a/MAAComponent-OTA-v5.1.1-alpha.1.d006.g91b0b8e4f_v5.1.1-alpha.1.d131.ge6367fd2a-win-x64.zip",
        "mirrors": [
          "https://agent.imgg.dev/MaaAssistantArknights/MaaRelease/releases/download/v5.1.1-alpha.1.d131.ge6367fd2a/MAAComponent-OTA-v5.1.1-alpha.1.d006.g91b0b8e4f_v5.1.1-alpha.1.d131.ge6367fd2a-win-x64.zip",
          "https://maa.r2.imgg.dev/MaaAssistantArknights/MaaRelease/releases/download/v5.1.1-alpha.1.d131.ge6367fd2a/MAAComponent-OTA-v5.1.1-alpha.1.d006.g91b0b8e4f_v5.1.1-alpha.1.d131.ge6367fd2a-win-x64.zip"
        ]
      },
      {
        "name": "MAAComponent-OTA-v5.1.1-alpha.1.d010.g6c79ff49e_v5.1.1-alpha.1.d131.ge6367fd2a-win-x64.zip",
        "size": 8298558,
        "browser_download_url": "https://github.com/MaaAssistantArknights/MaaRelease/releases/download/v5.1.1-alpha.1.d131.ge6367fd2a/MAAComponent-OTA-v5.1.1-alpha.1.d010.g6c79ff49e_v5.1.1-alpha.1.d131.ge6367fd2a-win-x64.zip",
        "mirrors": [
          "https://agent.imgg.dev/MaaAssistantArknights/MaaRelease/releases/download/v5.1.1-alpha.1.d131.ge6367fd2a/MAAComponent-OTA-v5.1.1-alpha.1.d010.g6c79ff49e_v5.1.1-alpha.1.d131.ge6367fd2a-win-x64.zip",
          "https://maa.r2.imgg.dev/MaaAssistantArknights/MaaRelease/releases/download/v5.1.1-alpha.1.d131.ge6367fd2a/MAAComponent-OTA-v5.1.1-alpha.1.d010.g6c79ff49e_v5.1.1-alpha.1.d131.ge6367fd2a-win-x64.zip"
        ]
      },
      {
        "name": "MAAComponent-OTA-v5.1.1-alpha.1.d013.gf4df22907_v5.1.1-alpha.1.d131.ge6367fd2a-win-x64.zip",
        "size": 8298558,
        "browser_download_url": "https://github.com/MaaAssistantArknights/MaaRelease/releases/download/v5.1.1-alpha.1.d131.ge6367fd2a/MAAComponent-OTA-v5.1.1-alpha.1.d013.gf4df22907_v5.1.1-alpha.1.d131.ge6367fd2a-win-x64.zip",
        "mirrors": [
          "https://agent.imgg.dev/MaaAssistantArknights/MaaRelease/releases/download/v5.1.1-alpha.1.d131.ge6367fd2a/MAAComponent-OTA-v5.1.1-alpha.1.d013.gf4df22907_v5.1.1-alpha.1.d131.ge6367fd2a-win-x64.zip",
          "https://maa.r2.imgg.dev/MaaAssistantArknights/MaaRelease/releases/download/v5.1.1-alpha.1.d131.ge6367fd2a/MAAComponent-OTA-v5.1.1-alpha.1.d013.gf4df22907_v5.1.1-alpha.1.d131.ge6367fd2a-win-x64.zip"
        ]
      },
      {
        "name": "MAAComponent-OTA-v5.1.1-alpha.1.d014.g4a464c14e_v5.1.1-alpha.1.d131.ge6367fd2a-win-x64.zip",
        "size": 8298558,
        "browser_download_url": "https://github.com/MaaAssistantArknights/MaaRelease/releases/download/v5.1.1-alpha.1.d131.ge6367fd2a/MAAComponent-OTA-v5.1.1-alpha.1.d014.g4a464c14e_v5.1.1-alpha.1.d131.ge6367fd2a-win-x64.zip",
        "mirrors": [
          "https://agent.imgg.dev/MaaAssistantArknights/MaaRelease/releases/download/v5.1.1-alpha.1.d131.ge6367fd2a/MAAComponent-OTA-v5.1.1-alpha.1.d014.g4a464c14e_v5.1.1-alpha.1.d131.ge6367fd2a-win-x64.zip",
          "https://maa.r2.imgg.dev/MaaAssistantArknights/MaaRelease/releases/download/v5.1.1-alpha.1.d131.ge6367fd2a/MAAComponent-OTA-v5.1.1-alpha.1.d014.g4a464c14e_v5.1.1-alpha.1.d131.ge6367fd2a-win-x64.zip"
        ]
      },
      {
        "name": "MAAComponent-OTA-v5.1.1-alpha.1.d022.g1a65cd840_v5.1.1-alpha.1.d131.ge6367fd2a-win-x64.zip",
        "size": 8265503,
        "browser_download_url": "https://github.com/MaaAssistantArknights/MaaRelease/releases/download/v5.1.1-alpha.1.d131.ge6367fd2a/MAAComponent-OTA-v5.1.1-alpha.1.d022.g1a65cd840_v5.1.1-alpha.1.d131.ge6367fd2a-win-x64.zip",
        "mirrors": [
          "https://agent.imgg.dev/MaaAssistantArknights/MaaRelease/releases/download/v5.1.1-alpha.1.d131.ge6367fd2a/MAAComponent-OTA-v5.1.1-alpha.1.d022.g1a65cd840_v5.1.1-alpha.1.d131.ge6367fd2a-win-x64.zip",
          "https://maa.r2.imgg.dev/MaaAssistantArknights/MaaRelease/releases/download/v5.1.1-alpha.1.d131.ge6367fd2a/MAAComponent-OTA-v5.1.1-alpha.1.d022.g1a65cd840_v5.1.1-alpha.1.d131.ge6367fd2a-win-x64.zip"
        ]
      },
      {
        "name": "MAAComponent-OTA-v5.1.1-alpha.1.d025.g15b537b0e_v5.1.1-alpha.1.d131.ge6367fd2a-win-x64.zip",
        "size": 8265503,
        "browser_download_url": "https://github.com/MaaAssistantArknights/MaaRelease/releases/download/v5.1.1-alpha.1.d131.ge6367fd2a/MAAComponent-OTA-v5.1.1-alpha.1.d025.g15b537b0e_v5.1.1-alpha.1.d131.ge6367fd2a-win-x64.zip",
        "mirrors": [
          "https://agent.imgg.dev/MaaAssistantArknights/MaaRelease/releases/download/v5.1.1-alpha.1.d131.ge6367fd2a/MAAComponent-OTA-v5.1.1-alpha.1.d025.g15b537b0e_v5.1.1-alpha.1.d131.ge6367fd2a-win-x64.zip",
          "https://maa.r2.imgg.dev/MaaAssistantArknights/MaaRelease/releases/download/v5.1.1-alpha.1.d131.ge6367fd2a/MAAComponent-OTA-v5.1.1-alpha.1.d025.g15b537b0e_v5.1.1-alpha.1.d131.ge6367fd2a-win-x64.zip"
        ]
      },
      {
        "name": "MAAComponent-OTA-v5.1.1-alpha.1.d029.g396460fe7_v5.1.1-alpha.1.d131.ge6367fd2a-win-x64.zip",
        "size": 8261708,
        "browser_download_url": "https://github.com/MaaAssistantArknights/MaaRelease/releases/download/v5.1.1-alpha.1.d131.ge6367fd2a/MAAComponent-OTA-v5.1.1-alpha.1.d029.g396460fe7_v5.1.1-alpha.1.d131.ge6367fd2a-win-x64.zip",
        "mirrors": [
          "https://agent.imgg.dev/MaaAssistantArknights/MaaRelease/releases/download/v5.1.1-alpha.1.d131.ge6367fd2a/MAAComponent-OTA-v5.1.1-alpha.1.d029.g396460fe7_v5.1.1-alpha.1.d131.ge6367fd2a-win-x64.zip",
          "https://maa.r2.imgg.dev/MaaAssistantArknights/MaaRelease/releases/download/v5.1.1-alpha.1.d131.ge6367fd2a/MAAComponent-OTA-v5.1.1-alpha.1.d029.g396460fe7_v5.1.1-alpha.1.d131.ge6367fd2a-win-x64.zip"
        ]
      },
      {
        "name": "MAAComponent-OTA-v5.1.1-alpha.1.d030.g078feead6_v5.1.1-alpha.1.d131.ge6367fd2a-win-x64.zip",
        "size": 8261708,
        "browser_download_url": "https://github.com/MaaAssistantArknights/MaaRelease/releases/download/v5.1.1-alpha.1.d131.ge6367fd2a/MAAComponent-OTA-v5.1.1-alpha.1.d030.g078feead6_v5.1.1-alpha.1.d131.ge6367fd2a-win-x64.zip",
        "mirrors": [
          "https://agent.imgg.dev/MaaAssistantArknights/MaaRelease/releases/download/v5.1.1-alpha.1.d131.ge6367fd2a/MAAComponent-OTA-v5.1.1-alpha.1.d030.g078feead6_v5.1.1-alpha.1.d131.ge6367fd2a-win-x64.zip",
          "https://maa.r2.imgg.dev/MaaAssistantArknights/MaaRelease/releases/download/v5.1.1-alpha.1.d131.ge6367fd2a/MAAComponent-OTA-v5.1.1-alpha.1.d030.g078feead6_v5.1.1-alpha.1.d131.ge6367fd2a-win-x64.zip"
        ]
      },
      {
        "name": "MAAComponent-OTA-v5.1.1-alpha.1.d051.g573a16e14_v5.1.1-alpha.1.d131.ge6367fd2a-win-x64.zip",
        "size": 8259356,
        "browser_download_url": "https://github.com/MaaAssistantArknights/MaaRelease/releases/download/v5.1.1-alpha.1.d131.ge6367fd2a/MAAComponent-OTA-v5.1.1-alpha.1.d051.g573a16e14_v5.1.1-alpha.1.d131.ge6367fd2a-win-x64.zip",
        "mirrors": [
          "https://agent.imgg.dev/MaaAssistantArknights/MaaRelease/releases/download/v5.1.1-alpha.1.d131.ge6367fd2a/MAAComponent-OTA-v5.1.1-alpha.1.d051.g573a16e14_v5.1.1-alpha.1.d131.ge6367fd2a-win-x64.zip",
          "https://maa.r2.imgg.dev/MaaAssistantArknights/MaaRelease/releases/download/v5.1.1-alpha.1.d131.ge6367fd2a/MAAComponent-OTA-v5.1.1-alpha.1.d051.g573a16e14_v5.1.1-alpha.1.d131.ge6367fd2a-win-x64.zip"
        ]
      },
      {
        "name": "MAAComponent-OTA-v5.1.1-alpha.1.d054.gac3dcd917_v5.1.1-alpha.1.d131.ge6367fd2a-win-x64.zip",
        "size": 8169844,
        "browser_download_url": "https://github.com/MaaAssistantArknights/MaaRelease/releases/download/v5.1.1-alpha.1.d131.ge6367fd2a/MAAComponent-OTA-v5.1.1-alpha.1.d054.gac3dcd917_v5.1.1-alpha.1.d131.ge6367fd2a-win-x64.zip",
        "mirrors": [
          "https://agent.imgg.dev/MaaAssistantArknights/MaaRelease/releases/download/v5.1.1-alpha.1.d131.ge6367fd2a/MAAComponent-OTA-v5.1.1-alpha.1.d054.gac3dcd917_v5.1.1-alpha.1.d131.ge6367fd2a-win-x64.zip",
          "https://maa.r2.imgg.dev/MaaAssistantArknights/MaaRelease/releases/download/v5.1.1-alpha.1.d131.ge6367fd2a/MAAComponent-OTA-v5.1.1-alpha.1.d054.gac3dcd917_v5.1.1-alpha.1.d131.ge6367fd2a-win-x64.zip"
        ]
      },
      {
        "name": "MAAComponent-OTA-v5.1.1-alpha.1.d059.g762e43303_v5.1.1-alpha.1.d131.ge6367fd2a-win-x64.zip",
        "size": 8104980,
        "browser_download_url": "https://github.com/MaaAssistantArknights/MaaRelease/releases/download/v5.1.1-alpha.1.d131.ge6367fd2a/MAAComponent-OTA-v5.1.1-alpha.1.d059.g762e43303_v5.1.1-alpha.1.d131.ge6367fd2a-win-x64.zip",
        "mirrors": [
          "https://agent.imgg.dev/MaaAssistantArknights/MaaRelease/releases/download/v5.1.1-alpha.1.d131.ge6367fd2a/MAAComponent-OTA-v5.1.1-alpha.1.d059.g762e43303_v5.1.1-alpha.1.d131.ge6367fd2a-win-x64.zip",
          "https://maa.r2.imgg.dev/MaaAssistantArknights/MaaRelease/releases/download/v5.1.1-alpha.1.d131.ge6367fd2a/MAAComponent-OTA-v5.1.1-alpha.1.d059.g762e43303_v5.1.1-alpha.1.d131.ge6367fd2a-win-x64.zip"
        ]
      },
      {
        "name": "MAAComponent-OTA-v5.1.1-alpha.1.d068.g9de91e870_v5.1.1-alpha.1.d131.ge6367fd2a-win-x64.zip",
        "size": 8098574,
        "browser_download_url": "https://github.com/MaaAssistantArknights/MaaRelease/releases/download/v5.1.1-alpha.1.d131.ge6367fd2a/MAAComponent-OTA-v5.1.1-alpha.1.d068.g9de91e870_v5.1.1-alpha.1.d131.ge6367fd2a-win-x64.zip",
        "mirrors": [
          "https://agent.imgg.dev/MaaAssistantArknights/MaaRelease/releases/download/v5.1.1-alpha.1.d131.ge6367fd2a/MAAComponent-OTA-v5.1.1-alpha.1.d068.g9de91e870_v5.1.1-alpha.1.d131.ge6367fd2a-win-x64.zip",
          "https://maa.r2.imgg.dev/MaaAssistantArknights/MaaRelease/releases/download/v5.1.1-alpha.1.d131.ge6367fd2a/MAAComponent-OTA-v5.1.1-alpha.1.d068.g9de91e870_v5.1.1-alpha.1.d131.ge6367fd2a-win-x64.zip"
        ]
      },
      {
        "name": "MAAComponent-OTA-v5.1.1-alpha.1.d069.g33dac7196_v5.1.1-alpha.1.d131.ge6367fd2a-win-x64.zip",
        "size": 8094989,
        "browser_download_url": "https://github.com/MaaAssistantArknights/MaaRelease/releases/download/v5.1.1-alpha.1.d131.ge6367fd2a/MAAComponent-OTA-v5.1.1-alpha.1.d069.g33dac7196_v5.1.1-alpha.1.d131.ge6367fd2a-win-x64.zip",
        "mirrors": [
          "https://agent.imgg.dev/MaaAssistantArknights/MaaRelease/releases/download/v5.1.1-alpha.1.d131.ge6367fd2a/MAAComponent-OTA-v5.1.1-alpha.1.d069.g33dac7196_v5.1.1-alpha.1.d131.ge6367fd2a-win-x64.zip",
          "https://maa.r2.imgg.dev/MaaAssistantArknights/MaaRelease/releases/download/v5.1.1-alpha.1.d131.ge6367fd2a/MAAComponent-OTA-v5.1.1-alpha.1.d069.g33dac7196_v5.1.1-alpha.1.d131.ge6367fd2a-win-x64.zip"
        ]
      },
      {
        "name": "MAAComponent-OTA-v5.1.1-alpha.1.d081.g61fbb1209_v5.1.1-alpha.1.d131.ge6367fd2a-win-x64.zip",
        "size": 8092363,
        "browser_download_url": "https://github.com/MaaAssistantArknights/MaaRelease/releases/download/v5.1.1-alpha.1.d131.ge6367fd2a/MAAComponent-OTA-v5.1.1-alpha.1.d081.g61fbb1209_v5.1.1-alpha.1.d131.ge6367fd2a-win-x64.zip",
        "mirrors": [
          "https://agent.imgg.dev/MaaAssistantArknights/MaaRelease/releases/download/v5.1.1-alpha.1.d131.ge6367fd2a/MAAComponent-OTA-v5.1.1-alpha.1.d081.g61fbb1209_v5.1.1-alpha.1.d131.ge6367fd2a-win-x64.zip",
          "https://maa.r2.imgg.dev/MaaAssistantArknights/MaaRelease/releases/download/v5.1.1-alpha.1.d131.ge6367fd2a/MAAComponent-OTA-v5.1.1-alpha.1.d081.g61fbb1209_v5.1.1-alpha.1.d131.ge6367fd2a-win-x64.zip"
        ]
      },
      {
        "name": "MAAComponent-OTA-v5.1.1-alpha.1.d083.g55345e6ef_v5.1.1-alpha.1.d131.ge6367fd2a-win-x64.zip",
        "size": 8092363,
        "browser_download_url": "https://github.com/MaaAssistantArknights/MaaRelease/releases/download/v5.1.1-alpha.1.d131.ge6367fd2a/MAAComponent-OTA-v5.1.1-alpha.1.d083.g55345e6ef_v5.1.1-alpha.1.d131.ge6367fd2a-win-x64.zip",
        "mirrors": [
          "https://agent.imgg.dev/MaaAssistantArknights/MaaRelease/releases/download/v5.1.1-alpha.1.d131.ge6367fd2a/MAAComponent-OTA-v5.1.1-alpha.1.d083.g55345e6ef_v5.1.1-alpha.1.d131.ge6367fd2a-win-x64.zip",
          "https://maa.r2.imgg.dev/MaaAssistantArknights/MaaRelease/releases/download/v5.1.1-alpha.1.d131.ge6367fd2a/MAAComponent-OTA-v5.1.1-alpha.1.d083.g55345e6ef_v5.1.1-alpha.1.d131.ge6367fd2a-win-x64.zip"
        ]
      },
      {
        "name": "MAAComponent-OTA-v5.1.1-alpha.1.d113.g637b8be32_v5.1.1-alpha.1.d131.ge6367fd2a-win-x64.zip",
        "size": 7881143,
        "browser_download_url": "https://github.com/MaaAssistantArknights/MaaRelease/releases/download/v5.1.1-alpha.1.d131.ge6367fd2a/MAAComponent-OTA-v5.1.1-alpha.1.d113.g637b8be32_v5.1.1-alpha.1.d131.ge6367fd2a-win-x64.zip",
        "mirrors": [
          "https://agent.imgg.dev/MaaAssistantArknights/MaaRelease/releases/download/v5.1.1-alpha.1.d131.ge6367fd2a/MAAComponent-OTA-v5.1.1-alpha.1.d113.g637b8be32_v5.1.1-alpha.1.d131.ge6367fd2a-win-x64.zip",
          "https://maa.r2.imgg.dev/MaaAssistantArknights/MaaRelease/releases/download/v5.1.1-alpha.1.d131.ge6367fd2a/MAAComponent-OTA-v5.1.1-alpha.1.d113.g637b8be32_v5.1.1-alpha.1.d131.ge6367fd2a-win-x64.zip"
        ]
      },
      {
        "name": "MAAComponent-OTA-v5.1.1-alpha.1.d116.g5397727f9_v5.1.1-alpha.1.d131.ge6367fd2a-win-x64.zip",
        "size": 7758530,
        "browser_download_url": "https://github.com/MaaAssistantArknights/MaaRelease/releases/download/v5.1.1-alpha.1.d131.ge6367fd2a/MAAComponent-OTA-v5.1.1-alpha.1.d116.g5397727f9_v5.1.1-alpha.1.d131.ge6367fd2a-win-x64.zip",
        "mirrors": [
          "https://agent.imgg.dev/MaaAssistantArknights/MaaRelease/releases/download/v5.1.1-alpha.1.d131.ge6367fd2a/MAAComponent-OTA-v5.1.1-alpha.1.d116.g5397727f9_v5.1.1-alpha.1.d131.ge6367fd2a-win-x64.zip",
          "https://maa.r2.imgg.dev/MaaAssistantArknights/MaaRelease/releases/download/v5.1.1-alpha.1.d131.ge6367fd2a/MAAComponent-OTA-v5.1.1-alpha.1.d116.g5397727f9_v5.1.1-alpha.1.d131.ge6367fd2a-win-x64.zip"
        ]
      },
      {
        "name": "MAAComponent-OTA-v5.1.1-alpha.1.d118.g999f9087b_v5.1.1-alpha.1.d131.ge6367fd2a-win-x64.zip",
        "size": 7727868,
        "browser_download_url": "https://github.com/MaaAssistantArknights/MaaRelease/releases/download/v5.1.1-alpha.1.d131.ge6367fd2a/MAAComponent-OTA-v5.1.1-alpha.1.d118.g999f9087b_v5.1.1-alpha.1.d131.ge6367fd2a-win-x64.zip",
        "mirrors": [
          "https://agent.imgg.dev/MaaAssistantArknights/MaaRelease/releases/download/v5.1.1-alpha.1.d131.ge6367fd2a/MAAComponent-OTA-v5.1.1-alpha.1.d118.g999f9087b_v5.1.1-alpha.1.d131.ge6367fd2a-win-x64.zip",
          "https://maa.r2.imgg.dev/MaaAssistantArknights/MaaRelease/releases/download/v5.1.1-alpha.1.d131.ge6367fd2a/MAAComponent-OTA-v5.1.1-alpha.1.d118.g999f9087b_v5.1.1-alpha.1.d131.ge6367fd2a-win-x64.zip"
        ]
      },
      {
        "name": "MAAComponent-OTA-v5.1.1-alpha.1.d119.g9b2da02bd_v5.1.1-alpha.1.d131.ge6367fd2a-win-x64.zip",
        "size": 7727868,
        "browser_download_url": "https://github.com/MaaAssistantArknights/MaaRelease/releases/download/v5.1.1-alpha.1.d131.ge6367fd2a/MAAComponent-OTA-v5.1.1-alpha.1.d119.g9b2da02bd_v5.1.1-alpha.1.d131.ge6367fd2a-win-x64.zip",
        "mirrors": [
          "https://agent.imgg.dev/MaaAssistantArknights/MaaRelease/releases/download/v5.1.1-alpha.1.d131.ge6367fd2a/MAAComponent-OTA-v5.1.1-alpha.1.d119.g9b2da02bd_v5.1.1-alpha.1.d131.ge6367fd2a-win-x64.zip",
          "https://maa.r2.imgg.dev/MaaAssistantArknights/MaaRelease/releases/download/v5.1.1-alpha.1.d131.ge6367fd2a/MAAComponent-OTA-v5.1.1-alpha.1.d119.g9b2da02bd_v5.1.1-alpha.1.d131.ge6367fd2a-win-x64.zip"
        ]
      },
      {
        "name": "MAAComponent-OTA-v5.1.1-alpha.1.d125.g690c99c4e_v5.1.1-alpha.1.d131.ge6367fd2a-win-x64.zip",
        "size": 7716905,
        "browser_download_url": "https://github.com/MaaAssistantArknights/MaaRelease/releases/download/v5.1.1-alpha.1.d131.ge6367fd2a/MAAComponent-OTA-v5.1.1-alpha.1.d125.g690c99c4e_v5.1.1-alpha.1.d131.ge6367fd2a-win-x64.zip",
        "mirrors": [
          "https://agent.imgg.dev/MaaAssistantArknights/MaaRelease/releases/download/v5.1.1-alpha.1.d131.ge6367fd2a/MAAComponent-OTA-v5.1.1-alpha.1.d125.g690c99c4e_v5.1.1-alpha.1.d131.ge6367fd2a-win-x64.zip",
          "https://maa.r2.imgg.dev/MaaAssistantArknights/MaaRelease/releases/download/v5.1.1-alpha.1.d131.ge6367fd2a/MAAComponent-OTA-v5.1.1-alpha.1.d125.g690c99c4e_v5.1.1-alpha.1.d131.ge6367fd2a-win-x64.zip"
        ]
      }
    ],
    "tarball_url": "https://api.github.com/repos/MaaAssistantArknights/MaaRelease/tarball/v5.1.1-alpha.1.d131.ge6367fd2a",
    "zipball_url": "https://api.github.com/repos/MaaAssistantArknights/MaaRelease/zipball/v5.1.1-alpha.1.d131.ge6367fd2a",
    "body": "\n\n**Full Changelog**: [v5.1.0 -> alpha/v5.1.1-alpha.1.d131.ge6367fd2a](https://github.com/MaaAssistantArknights/MaaAssistantArknights/compare/v5.1.0...alpha/v5.1.1-alpha.1.d131.ge6367fd2a)"
  }
}