{
  "version": "v6.3.6-alpha.1.d001.gef57632ad",
  "details": {
    "url": "https://api.github.com/repos/MaaAssistantArknights/MaaRelease/releases/290611215",
    "assets_url": "https://api.github.com/repos/MaaAssistantArknights/MaaRelease/releases/290611215/assets",
    "upload_url": "https://uploads.github.com/repos/MaaAssistantArknights/MaaRelease/releases/290611215/assets{?name,label}",
    "html_url": "https://github.com/MaaAssistantArknights/MaaRelease/releases/tag/v6.3.6-alpha.1.d001.gef57632ad",
    "id": 290611215,
    "node_id": "RE_kwDOIUyZWc4RUmAP",
    "tag_name": "v6.3.6-alpha.1.d001.gef57632ad",
    "target_commitish": "main",
    "name": "",
    "draft": false,
    "immutable": false,
    "prerelease": true,
    "created_at": "2026-02-25T22:27:52Z",
    "updated_at": "2026-02-25T22:30:18Z",
    "published_at": "2026-02-25T22:29:57Z",
    "assets": [
      {
        "name": "MAA-v6.3.6-alpha.1.d001.gef57632ad-win-x64.zip",
        "size": 186005984,
        "browser_download_url": "https://github.com/MaaAssistantArknights/MaaRelease/releases/download/v6.3.6-alpha.1.d001.gef57632ad/MAA-v6.3.6-alpha.1.d001.gef57632ad-win-x64.zip",
        "mirrors": []
      },
      {
        "name": "MAAComponent-OTA-v6.3.0-beta.5_v6.3.6-alpha.1.d001.gef57632ad-win-x64.zip",
        "size": 7528493,
        "browser_download_url": "https://github.com/MaaAssistantArknights/MaaRelease/releases/download/v6.3.6-alpha.1.d001.gef57632ad/MAAComponent-OTA-v6.3.0-beta.5_v6.3.6-alpha.1.d001.gef57632ad-win-x64.zip",
        "mirrors": []
      },
      {
        "name": "MAAComponent-OTA-v6.3.0-beta.6_v6.3.6-alpha.1.d001.gef57632ad-win-x64.zip",
        "size": 6855576,
        "browser_download_url": "https://github.com/MaaAssistantArknights/MaaRelease/releases/download/v6.3.6-alpha.1.d001.gef57632ad/MAAComponent-OTA-v6.3.0-beta.6_v6.3.6-alpha.1.d001.gef57632ad-win-x64.zip",
        "mirrors": []
      },
      {
        "name": "MAAComponent-OTA-v6.3.0-beta.7_v6.3.6-alpha.1.d001.gef57632ad-win-x64.zip",
        "size": 6855576,
        "browser_download_url": "https://github.com/MaaAssistantArknights/MaaRelease/releases/download/v6.3.6-alpha.1.d001.gef57632ad/MAAComponent-OTA-v6.3.0-beta.7_v6.3.6-alpha.1.d001.gef57632ad-win-x64.zip",
        "mirrors": []
      },
      {
        "name": "MAAComponent-OTA-v6.3.0-beta.8_v6.3.6-alpha.1.d001.gef57632ad-win-x64.zip",
        "size": 6787823,
        "browser_download_url": "https://github.com/MaaAssistantArknights/MaaRelease/releases/download/v6.3.6-alpha.1.d001.gef57632ad/MAAComponent-OTA-v6.3.0-beta.8_v6.3.6-alpha.1.d001.gef57632ad-win-x64.zip",
        "mirrors": []
      },
      {
        "name": "MAAComponent-OTA-v6.3.0_v6.3.6-alpha.1.d001.gef57632ad-win-x64.zip",
        "size": 5675106,
        "browser_download_url": "https://github.com/MaaAssistantArknights/MaaRelease/releases/download/v6.3.6-alpha.1.d001.gef57632ad/MAAComponent-OTA-v6.3.0_v6.3.6-alpha.1.d001.gef57632ad-win-x64.zip",
        "mirrors": []
      },
      {
        "name": "MAAComponent-OTA-v6.3.1_v6.3.6-alpha.1.d001.gef57632ad-win-x64.zip",
        "size": 5619088,
        "browser_download_url": "https://github.com/MaaAssistantArknights/MaaRelease/releases/download/v6.3.6-alpha.1.d001.gef57632ad/MAAComponent-OTA-v6.3.1_v6.3.6-alpha.1.d001.gef57632ad-win-x64.zip",
        "mirrors": []
      },
      {
        "name": "MAAComponent-OTA-v6.3.2_v6.3.6-alpha.1.d001.gef57632ad-win-x64.zip",
        "size": 5388547,
        "browser_download_url": "https://github.com/MaaAssistantArknights/MaaRelease/releases/download/v6.3.6-alpha.1.d001.gef57632ad/MAAComponent-OTA-v6.3.2_v6.3.6-alpha.1.d001.gef57632ad-win-x64.zip",
        "mirrors": []
      },
      {
        "name": "MAAComponent-OTA-v6.3.3-alpha.1.d001.ge7362d2d3_v6.3.6-alpha.1.d001.gef57632ad-win-x64.zip",
        "size": 5291853,
        "browser_download_url": "https://github.com/MaaAssistantArknights/MaaRelease/releases/download/v6.3.6-alpha.1.d001.gef57632ad/MAAComponent-OTA-v6.3.3-alpha.1.d001.ge7362d2d3_v6.3.6-alpha.1.d001.gef57632ad-win-x64.zip",
        "mirrors": []
      },
      {
        "name": "MAAComponent-OTA-v6.3.3-alpha.1.d007.g0817bc1c9_v6.3.6-alpha.1.d001.gef57632ad-win-x64.zip",
        "size": 5280701,
        "browser_download_url": "https://github.com/MaaAssistantArknights/MaaRelease/releases/download/v6.3.6-alpha.1.d001.gef57632ad/MAAComponent-OTA-v6.3.3-alpha.1.d007.g0817bc1c9_v6.3.6-alpha.1.d001.gef57632ad-win-x64.zip",
        "mirrors": []
      },
      {
        "name": "MAAComponent-OTA-v6.3.3-alpha.1.d010.g01a2329d1_v6.3.6-alpha.1.d001.gef57632ad-win-x64.zip",
        "size": 5280359,
        "browser_download_url": "https://github.com/MaaAssistantArknights/MaaRelease/releases/download/v6.3.6-alpha.1.d001.gef57632ad/MAAComponent-OTA-v6.3.3-alpha.1.d010.g01a2329d1_v6.3.6-alpha.1.d001.gef57632ad-win-x64.zip",
        "mirrors": []
      },
      {
        "name": "MAAComponent-OTA-v6.3.3-alpha.1.d012.g0f5f3a2f8_v6.3.6-alpha.1.d001.gef57632ad-win-x64.zip",
        "size": 5280359,
        "browser_download_url": "https://github.com/MaaAssistantArknights/MaaRelease/releases/download/v6.3.6-alpha.1.d001.gef57632ad/MAAComponent-OTA-v6.3.3-alpha.1.d012.g0f5f3a2f8_v6.3.6-alpha.1.d001.gef57632ad-win-x64.zip",
        "mirrors": []
      },
      {
        "name": "MAAComponent-OTA-v6.3.3-alpha.1.d019.g1dd174291_v6.3.6-alpha.1.d001.gef57632ad-win-x64.zip",
        "size": 5280359,
        "browser_download_url": "https://github.com/MaaAssistantArknights/MaaRelease/releases/download/v6.3.6-alpha.1.d001.gef57632ad/MAAComponent-OTA-v6.3.3-alpha.1.d019.g1dd174291_v6.3.6-alpha.1.d001.gef57632ad-win-x64.zip",
        "mirrors": []
      },
      {
        "name": "MAAComponent-OTA-v6.3.3-alpha.1.d029.ge93d79202_v6.3.6-alpha.1.d001.gef57632ad-win-x64.zip",
        "size": 4603373,
        "browser_download_url": "https://github.com/MaaAssistantArknights/MaaRelease/releases/download/v6.3.6-alpha.1.d001.gef57632ad/MAAComponent-OTA-v6.3.3-alpha.1.d029.ge93d79202_v6.3.6-alpha.1.d001.gef57632ad-win-x64.zip",
        "mirrors": []
      },
      {
        "name": "MAAComponent-OTA-v6.3.3_v6.3.6-alpha.1.d001.gef57632ad-win-x64.zip",
        "size": 4573869,
        "browser_download_url": "https://github.com/MaaAssistantArknights/MaaRelease/releases/download/v6.3.6-alpha.1.d001.gef57632ad/MAAComponent-OTA-v6.3.3_v6.3.6-alpha.1.d001.gef57632ad-win-x64.zip",
        "mirrors": []
      },
      {
        "name": "MAAComponent-OTA-v6.3.4_v6.3.6-alpha.1.d001.gef57632ad-win-x64.zip",
        "size": 4573313,
        "browser_download_url": "https://github.com/MaaAssistantArknights/MaaRelease/releases/download/v6.3.6-alpha.1.d001.gef57632ad/MAAComponent-OTA-v6.3.4_v6.3.6-alpha.1.d001.gef57632ad-win-x64.zip",
        "mirrors": []
      },
      {
        "name": "MAAComponent-OTA-v6.3.5_v6.3.6-alpha.1.d001.gef57632ad-win-x64.zip",
        "size": 4545298,
        "browser_download_url": "https://github.com/MaaAssistantArknights/MaaRelease/releases/download/v6.3.6-alpha.1.d001.gef57632ad/MAAComponent-OTA-v6.3.5_v6.3.6-alpha.1.d001.gef57632ad-win-x64.zip",
        "mirrors": []
      }
    ],
    "tarball_url": "https://api.github.com/repos/MaaAssistantArknights/MaaRelease/tarball/v6.3.6-alpha.1.d001.gef57632ad",
    "zipball_url": "https://api.github.com/repos/MaaAssistantArknights/MaaRelease/zipball/v6.3.6-alpha.1.d001.gef57632ad",
    "body": "**Full Changelog**: [v6.3.5 -> alpha/v6.3.6-alpha.1.d001.gef57632ad](https://github.com/MaaAssistantArknights/MaaAssistantArknights/compare/v6.3.5...alpha/v6.3.6-alpha.1.d001.gef57632ad)"
  }
}