{
  "version": "v6.0.1-alpha.1.d004.g199ab432f",
  "details": {
    "url": "https://api.github.com/repos/MaaAssistantArknights/MaaRelease/releases/269697582",
    "assets_url": "https://api.github.com/repos/MaaAssistantArknights/MaaRelease/releases/269697582/assets",
    "upload_url": "https://uploads.github.com/repos/MaaAssistantArknights/MaaRelease/releases/269697582/assets{?name,label}",
    "html_url": "https://github.com/MaaAssistantArknights/MaaRelease/releases/tag/v6.0.1-alpha.1.d004.g199ab432f",
    "id": 269697582,
    "node_id": "RE_kwDOIUyZWc4QE0Iu",
    "tag_name": "v6.0.1-alpha.1.d004.g199ab432f",
    "target_commitish": "main",
    "name": "",
    "draft": false,
    "immutable": false,
    "prerelease": true,
    "created_at": "2025-12-11T22:23:49Z",
    "updated_at": "2025-12-11T22:25:43Z",
    "published_at": "2025-12-11T22:25:22Z",
    "assets": [
      {
        "name": "MAA-v6.0.1-alpha.1.d004.g199ab432f-win-x64.zip",
        "size": 180902600,
        "browser_download_url": "https://github.com/MaaAssistantArknights/MaaRelease/releases/download/v6.0.1-alpha.1.d004.g199ab432f/MAA-v6.0.1-alpha.1.d004.g199ab432f-win-x64.zip",
        "mirrors": [
          "https://ota2.maa.plus/v6.0.1-alpha.1.d004.g199ab432f/MAA-v6.0.1-alpha.1.d004.g199ab432f-win-x64.zip"
        ]
      },
      {
        "name": "MAAComponent-OTA-v5.28.0-beta.2_v6.0.1-alpha.1.d004.g199ab432f-win-x64.zip",
        "size": 20374679,
        "browser_download_url": "https://github.com/MaaAssistantArknights/MaaRelease/releases/download/v6.0.1-alpha.1.d004.g199ab432f/MAAComponent-OTA-v5.28.0-beta.2_v6.0.1-alpha.1.d004.g199ab432f-win-x64.zip",
        "mirrors": [
          "https://ota2.maa.plus/v6.0.1-alpha.1.d004.g199ab432f/MAAComponent-OTA-v5.28.0-beta.2_v6.0.1-alpha.1.d004.g199ab432f-win-x64.zip"
        ]
      },
      {
        "name": "MAAComponent-OTA-v5.28.0_v6.0.1-alpha.1.d004.g199ab432f-win-x64.zip",
        "size": 20366538,
        "browser_download_url": "https://github.com/MaaAssistantArknights/MaaRelease/releases/download/v6.0.1-alpha.1.d004.g199ab432f/MAAComponent-OTA-v5.28.0_v6.0.1-alpha.1.d004.g199ab432f-win-x64.zip",
        "mirrors": [
          "https://ota2.maa.plus/v6.0.1-alpha.1.d004.g199ab432f/MAAComponent-OTA-v5.28.0_v6.0.1-alpha.1.d004.g199ab432f-win-x64.zip"
        ]
      },
      {
        "name": "MAAComponent-OTA-v5.28.1_v6.0.1-alpha.1.d004.g199ab432f-win-x64.zip",
        "size": 15681270,
        "browser_download_url": "https://github.com/MaaAssistantArknights/MaaRelease/releases/download/v6.0.1-alpha.1.d004.g199ab432f/MAAComponent-OTA-v5.28.1_v6.0.1-alpha.1.d004.g199ab432f-win-x64.zip",
        "mirrors": [
          "https://ota2.maa.plus/v6.0.1-alpha.1.d004.g199ab432f/MAAComponent-OTA-v5.28.1_v6.0.1-alpha.1.d004.g199ab432f-win-x64.zip"
        ]
      },
      {
        "name": "MAAComponent-OTA-v5.28.2_v6.0.1-alpha.1.d004.g199ab432f-win-x64.zip",
        "size": 15625792,
        "browser_download_url": "https://github.com/MaaAssistantArknights/MaaRelease/releases/download/v6.0.1-alpha.1.d004.g199ab432f/MAAComponent-OTA-v5.28.2_v6.0.1-alpha.1.d004.g199ab432f-win-x64.zip",
        "mirrors": [
          "https://ota2.maa.plus/v6.0.1-alpha.1.d004.g199ab432f/MAAComponent-OTA-v5.28.2_v6.0.1-alpha.1.d004.g199ab432f-win-x64.zip"
        ]
      },
      {
        "name": "MAAComponent-OTA-v5.28.3_v6.0.1-alpha.1.d004.g199ab432f-win-x64.zip",
        "size": 15389420,
        "browser_download_url": "https://github.com/MaaAssistantArknights/MaaRelease/releases/download/v6.0.1-alpha.1.d004.g199ab432f/MAAComponent-OTA-v5.28.3_v6.0.1-alpha.1.d004.g199ab432f-win-x64.zip",
        "mirrors": [
          "https://ota2.maa.plus/v6.0.1-alpha.1.d004.g199ab432f/MAAComponent-OTA-v5.28.3_v6.0.1-alpha.1.d004.g199ab432f-win-x64.zip"
        ]
      },
      {
        "name": "MAAComponent-OTA-v5.28.4_v6.0.1-alpha.1.d004.g199ab432f-win-x64.zip",
        "size": 15132058,
        "browser_download_url": "https://github.com/MaaAssistantArknights/MaaRelease/releases/download/v6.0.1-alpha.1.d004.g199ab432f/MAAComponent-OTA-v5.28.4_v6.0.1-alpha.1.d004.g199ab432f-win-x64.zip",
        "mirrors": [
          "https://ota2.maa.plus/v6.0.1-alpha.1.d004.g199ab432f/MAAComponent-OTA-v5.28.4_v6.0.1-alpha.1.d004.g199ab432f-win-x64.zip"
        ]
      },
      {
        "name": "MAAComponent-OTA-v5.28.5-alpha.1.d001.g2947f9fe9_v6.0.1-alpha.1.d004.g199ab432f-win-x64.zip",
        "size": 15082460,
        "browser_download_url": "https://github.com/MaaAssistantArknights/MaaRelease/releases/download/v6.0.1-alpha.1.d004.g199ab432f/MAAComponent-OTA-v5.28.5-alpha.1.d001.g2947f9fe9_v6.0.1-alpha.1.d004.g199ab432f-win-x64.zip",
        "mirrors": [
          "https://ota2.maa.plus/v6.0.1-alpha.1.d004.g199ab432f/MAAComponent-OTA-v5.28.5-alpha.1.d001.g2947f9fe9_v6.0.1-alpha.1.d004.g199ab432f-win-x64.zip"
        ]
      },
      {
        "name": "MAAComponent-OTA-v5.28.5-alpha.1.d003.g82fd1c074_v6.0.1-alpha.1.d004.g199ab432f-win-x64.zip",
        "size": 15082460,
        "browser_download_url": "https://github.com/MaaAssistantArknights/MaaRelease/releases/download/v6.0.1-alpha.1.d004.g199ab432f/MAAComponent-OTA-v5.28.5-alpha.1.d003.g82fd1c074_v6.0.1-alpha.1.d004.g199ab432f-win-x64.zip",
        "mirrors": [
          "https://ota2.maa.plus/v6.0.1-alpha.1.d004.g199ab432f/MAAComponent-OTA-v5.28.5-alpha.1.d003.g82fd1c074_v6.0.1-alpha.1.d004.g199ab432f-win-x64.zip"
        ]
      },
      {
        "name": "MAAComponent-OTA-v5.28.5-alpha.1.d011.g07844d61d_v6.0.1-alpha.1.d004.g199ab432f-win-x64.zip",
        "size": 15026971,
        "browser_download_url": "https://github.com/MaaAssistantArknights/MaaRelease/releases/download/v6.0.1-alpha.1.d004.g199ab432f/MAAComponent-OTA-v5.28.5-alpha.1.d011.g07844d61d_v6.0.1-alpha.1.d004.g199ab432f-win-x64.zip",
        "mirrors": [
          "https://ota2.maa.plus/v6.0.1-alpha.1.d004.g199ab432f/MAAComponent-OTA-v5.28.5-alpha.1.d011.g07844d61d_v6.0.1-alpha.1.d004.g199ab432f-win-x64.zip"
        ]
      },
      {
        "name": "MAAComponent-OTA-v5.28.5_v6.0.1-alpha.1.d004.g199ab432f-win-x64.zip",
        "size": 15076569,
        "browser_download_url": "https://github.com/MaaAssistantArknights/MaaRelease/releases/download/v6.0.1-alpha.1.d004.g199ab432f/MAAComponent-OTA-v5.28.5_v6.0.1-alpha.1.d004.g199ab432f-win-x64.zip",
        "mirrors": [
          "https://ota2.maa.plus/v6.0.1-alpha.1.d004.g199ab432f/MAAComponent-OTA-v5.28.5_v6.0.1-alpha.1.d004.g199ab432f-win-x64.zip"
        ]
      },
      {
        "name": "MAAComponent-OTA-v5.28.6-alpha.1.d014.g7d4c42822_v6.0.1-alpha.1.d004.g199ab432f-win-x64.zip",
        "size": 4413979,
        "browser_download_url": "https://github.com/MaaAssistantArknights/MaaRelease/releases/download/v6.0.1-alpha.1.d004.g199ab432f/MAAComponent-OTA-v5.28.6-alpha.1.d014.g7d4c42822_v6.0.1-alpha.1.d004.g199ab432f-win-x64.zip",
        "mirrors": [
          "https://ota2.maa.plus/v6.0.1-alpha.1.d004.g199ab432f/MAAComponent-OTA-v5.28.6-alpha.1.d014.g7d4c42822_v6.0.1-alpha.1.d004.g199ab432f-win-x64.zip"
        ]
      },
      {
        "name": "MAAComponent-OTA-v6.0.0-beta.1.d003.g0845c19dd_v6.0.1-alpha.1.d004.g199ab432f-win-x64.zip",
        "size": 4413979,
        "browser_download_url": "https://github.com/MaaAssistantArknights/MaaRelease/releases/download/v6.0.1-alpha.1.d004.g199ab432f/MAAComponent-OTA-v6.0.0-beta.1.d003.g0845c19dd_v6.0.1-alpha.1.d004.g199ab432f-win-x64.zip",
        "mirrors": [
          "https://ota2.maa.plus/v6.0.1-alpha.1.d004.g199ab432f/MAAComponent-OTA-v6.0.0-beta.1.d003.g0845c19dd_v6.0.1-alpha.1.d004.g199ab432f-win-x64.zip"
        ]
      },
      {
        "name": "MAAComponent-OTA-v6.0.0-beta.1_v6.0.1-alpha.1.d004.g199ab432f-win-x64.zip",
        "size": 4463725,
        "browser_download_url": "https://github.com/MaaAssistantArknights/MaaRelease/releases/download/v6.0.1-alpha.1.d004.g199ab432f/MAAComponent-OTA-v6.0.0-beta.1_v6.0.1-alpha.1.d004.g199ab432f-win-x64.zip",
        "mirrors": [
          "https://ota2.maa.plus/v6.0.1-alpha.1.d004.g199ab432f/MAAComponent-OTA-v6.0.0-beta.1_v6.0.1-alpha.1.d004.g199ab432f-win-x64.zip"
        ]
      },
      {
        "name": "MAAComponent-OTA-v6.0.0-beta.2_v6.0.1-alpha.1.d004.g199ab432f-win-x64.zip",
        "size": 4377148,
        "browser_download_url": "https://github.com/MaaAssistantArknights/MaaRelease/releases/download/v6.0.1-alpha.1.d004.g199ab432f/MAAComponent-OTA-v6.0.0-beta.2_v6.0.1-alpha.1.d004.g199ab432f-win-x64.zip",
        "mirrors": [
          "https://ota2.maa.plus/v6.0.1-alpha.1.d004.g199ab432f/MAAComponent-OTA-v6.0.0-beta.2_v6.0.1-alpha.1.d004.g199ab432f-win-x64.zip"
        ]
      },
      {
        "name": "MAAComponent-OTA-v6.0.0_v6.0.1-alpha.1.d004.g199ab432f-win-x64.zip",
        "size": 4101628,
        "browser_download_url": "https://github.com/MaaAssistantArknights/MaaRelease/releases/download/v6.0.1-alpha.1.d004.g199ab432f/MAAComponent-OTA-v6.0.0_v6.0.1-alpha.1.d004.g199ab432f-win-x64.zip",
        "mirrors": [
          "https://ota2.maa.plus/v6.0.1-alpha.1.d004.g199ab432f/MAAComponent-OTA-v6.0.0_v6.0.1-alpha.1.d004.g199ab432f-win-x64.zip"
        ]
      }
    ],
    "tarball_url": "https://api.github.com/repos/MaaAssistantArknights/MaaRelease/tarball/v6.0.1-alpha.1.d004.g199ab432f",
    "zipball_url": "https://api.github.com/repos/MaaAssistantArknights/MaaRelease/zipball/v6.0.1-alpha.1.d004.g199ab432f",
    "body": "### 修复 | Fix\r\n\r\n* OCR for RA2 @Constrat\r\n* Update StageTrader for EN IS @Constrat\r\n\r\n### 其他 | Other\r\n\r\n* update translations for SSS#8 tasks @Constrat\r\n* tweak copilot SSS tasks name @Constrat\r\n\n\n**Full Changelog**: [v6.0.0 -> alpha/v6.0.1-alpha.1.d004.g199ab432f](https://github.com/MaaAssistantArknights/MaaAssistantArknights/compare/v6.0.0...alpha/v6.0.1-alpha.1.d004.g199ab432f)",
    "mentions_count": 1
  }
}